ast_grep_py/__init__.py
ast_grep_py/ast_grep_py.cpython-312-darwin.so
ast_grep_py/ast_grep_py.pyi
ast_grep_py/py.typed
ast_grep_py-0.40.5.dist-info/METADATA
ast_grep_py-0.40.5.dist-info/WHEEL
ast_grep_py-0.40.5.dist-info/RECORD
